lnd_proto/__init__.py
lnd_proto/lightning_pb2.py
lnd_proto/lightning_pb2_grpc.py
lnd_proto/stateservice_pb2.py
lnd_proto/stateservice_pb2_grpc.py
lnd_proto/walletunlocker_pb2.py
lnd_proto/walletunlocker_pb2_grpc.py
lnd_proto-0.14.3b0.dist-info/WHEEL
lnd_proto-0.14.3b0.dist-info/METADATA
lnd_proto-0.14.3b0.dist-info/RECORD
